{
  "file": "config/build.sh",
  "classification": {
    "template": "software_project",
    "confidence": 1,
    "domain": "software",
    "docType": "Build Script"
  },
  "graphStructure": {
    "cypher": "CREATE (doc:Document {\n      id: \"User Management System Build Script\",\n      title: \"User Management System Build Script\",\n      domain: \"software\",\n      doc_type: \"Build Script\"\n    })\nCREATE (e0:Script {name: \"build_script\", language: \"Bash\", description: \"Shell script to build all components of the User Management System\"})\nCREATE (doc)-[:MENTIONS]->(e0)\nCREATE (e1:Module {name: \"TypeScript_API\", language: \"TypeScript\", description: \"API module built with TypeScript\"})\nCREATE (doc)-[:MENTIONS]->(e1)\nCREATE (e2:Module {name: \"Rust_database\", language: \"Rust\", description: \"Database module built with Rust\"})\nCREATE (doc)-[:MENTIONS]->(e2)\nCREATE (e3:Module {name: \"Python_pipeline\", language: \"Python\", description: \"Python pipeline module\"})\nCREATE (doc)-[:MENTIONS]->(e3)\nCREATE (e4:Module {name: \"frontend\", language: \"TypeScript\", description: \"Frontend module built with TypeScript\"})\nCREATE (doc)-[:MENTIONS]->(e4)\nCREATE (e5:Dependency {name: \"Node.js\", version: \"unknown\", description: \"JavaScript runtime required for building\"})\nCREATE (doc)-[:MENTIONS]->(e5)\nCREATE (e6:Dependency {name: \"Rust\", version: \"unknown\", description: \"Programming language required for building\"})\nCREATE (doc)-[:MENTIONS]->(e6)\nCREATE (e7:Dependency {name: \"Python_3\", version: \"3\", description: \"Python version 3 required for building\"})\nCREATE (doc)-[:MENTIONS]->(e7)\nCREATE (e8:Configuration {name: \"environment_setup\", description: \"Sets up Python virtual environment and installs dependencies\"})\nCREATE (doc)-[:MENTIONS]->(e8)\nCREATE (e9:API {name: \"TypeScript_API\", description: \"API server component\"})\nCREATE (doc)-[:MENTIONS]->(e9)\nCREATE (e10:Database {name: \"vector-db\", description: \"Vector database built with Rust\"})\nCREATE (doc)-[:MENTIONS]->(e10)\nCREATE (e11:Test {name: \"Rust_tests\", description: \"Tests for the Rust database module\"})\nCREATE (doc)-[:MENTIONS]->(e11)\nCREATE (e12:Test {name: \"Python_tests\", description: \"Tests for the Python pipeline module\"})\nCREATE (doc)-[:MENTIONS]->(e12)\nCREATE (e13:Documentation {name: \"build_summary\", description: \"Summary of build artifacts and service start instructions\"})\nCREATE (doc)-[:MENTIONS]->(e13)",
    "entities": [
      {
        "type": "Script",
        "properties": {
          "name": "build_script",
          "language": "Bash",
          "description": "Shell script to build all components of the User Management System"
        }
      },
      {
        "type": "Module",
        "properties": {
          "name": "TypeScript_API",
          "language": "TypeScript",
          "description": "API module built with TypeScript"
        }
      },
      {
        "type": "Module",
        "properties": {
          "name": "Rust_database",
          "language": "Rust",
          "description": "Database module built with Rust"
        }
      },
      {
        "type": "Module",
        "properties": {
          "name": "Python_pipeline",
          "language": "Python",
          "description": "Python pipeline module"
        }
      },
      {
        "type": "Module",
        "properties": {
          "name": "frontend",
          "language": "TypeScript",
          "description": "Frontend module built with TypeScript"
        }
      },
      {
        "type": "Dependency",
        "properties": {
          "name": "Node.js",
          "version": "unknown",
          "description": "JavaScript runtime required for building"
        }
      },
      {
        "type": "Dependency",
        "properties": {
          "name": "Rust",
          "version": "unknown",
          "description": "Programming language required for building"
        }
      },
      {
        "type": "Dependency",
        "properties": {
          "name": "Python_3",
          "version": "3",
          "description": "Python version 3 required for building"
        }
      },
      {
        "type": "Configuration",
        "properties": {
          "name": "environment_setup",
          "description": "Sets up Python virtual environment and installs dependencies"
        }
      },
      {
        "type": "API",
        "properties": {
          "name": "TypeScript_API",
          "description": "API server component"
        }
      },
      {
        "type": "Database",
        "properties": {
          "name": "vector-db",
          "description": "Vector database built with Rust"
        }
      },
      {
        "type": "Test",
        "properties": {
          "name": "Rust_tests",
          "description": "Tests for the Rust database module"
        }
      },
      {
        "type": "Test",
        "properties": {
          "name": "Python_tests",
          "description": "Tests for the Python pipeline module"
        }
      },
      {
        "type": "Documentation",
        "properties": {
          "name": "build_summary",
          "description": "Summary of build artifacts and service start instructions"
        }
      }
    ],
    "relationships": [
      {
        "type": "BUILDS",
        "source": "build_script",
        "target": "TypeScript_API",
        "properties": {}
      },
      {
        "type": "BUILDS",
        "source": "build_script",
        "target": "Rust_database",
        "properties": {}
      },
      {
        "type": "BUILDS",
        "source": "build_script",
        "target": "Python_pipeline",
        "properties": {}
      },
      {
        "type": "BUILDS",
        "source": "build_script",
        "target": "frontend",
        "properties": {}
      },
      {
        "type": "DEPENDS_ON",
        "source": "build_script",
        "target": "Node.js",
        "properties": {}
      },
      {
        "type": "DEPENDS_ON",
        "source": "build_script",
        "target": "Rust",
        "properties": {}
      },
      {
        "type": "DEPENDS_ON",
        "source": "build_script",
        "target": "Python_3",
        "properties": {}
      },
      {
        "type": "CONTAINS",
        "source": "build_script",
        "target": "environment_setup",
        "properties": {}
      },
      {
        "type": "CONTAINS",
        "source": "build_script",
        "target": "build_summary",
        "properties": {}
      },
      {
        "type": "TESTS",
        "source": "build_script",
        "target": "Rust_tests",
        "properties": {}
      },
      {
        "type": "TESTS",
        "source": "build_script",
        "target": "Python_tests",
        "properties": {}
      },
      {
        "type": "EXPOSES",
        "source": "TypeScript_API",
        "target": "API",
        "properties": {}
      },
      {
        "type": "ACCESSES",
        "source": "TypeScript_API",
        "target": "vector-db",
        "properties": {}
      },
      {
        "type": "DOCUMENTS",
        "source": "build_summary",
        "target": "TypeScript_API",
        "properties": {}
      },
      {
        "type": "DOCUMENTS",
        "source": "build_summary",
        "target": "vector-db",
        "properties": {}
      },
      {
        "type": "DOCUMENTS",
        "source": "build_summary",
        "target": "frontend",
        "properties": {}
      },
      {
        "type": "DOCUMENTS",
        "source": "build_summary",
        "target": "Python_pipeline",
        "properties": {}
      }
    ]
  },
  "fulltextMetadata": {
    "title": "User Management System Build Script",
    "domain": "software",
    "docType": "Build Script",
    "extractedFields": {
      "script_name": "build_script",
      "script_language": "Bash",
      "script_description": "Shell script to build all components of the User Management System",
      "module_name": [
        "TypeScript_API",
        "Rust_database",
        "Python_pipeline",
        "frontend"
      ],
      "module_language": [
        "TypeScript",
        "Rust",
        "Python",
        "TypeScript"
      ],
      "module_description": [
        "API module built with TypeScript",
        "Database module built with Rust",
        "Python pipeline module",
        "Frontend module built with TypeScript"
      ],
      "dependency_name": [
        "Node.js",
        "Rust",
        "Python_3"
      ],
      "dependency_version": [
        "unknown",
        "unknown",
        "3"
      ],
      "dependency_description": [
        "JavaScript runtime required for building",
        "Programming language required for building",
        "Python version 3 required for building"
      ],
      "configuration_name": "environment_setup",
      "configuration_description": "Sets up Python virtual environment and installs dependencies",
      "api_name": "TypeScript_API",
      "api_description": "API server component",
      "database_name": "vector-db",
      "database_description": "Vector database built with Rust",
      "test_name": [
        "Rust_tests",
        "Python_tests"
      ],
      "test_description": [
        "Tests for the Rust database module",
        "Tests for the Python pipeline module"
      ],
      "documentation_name": "build_summary",
      "documentation_description": "Summary of build artifacts and service start instructions"
    },
    "keywords": [
      "echo",
      "build",
      "rust",
      "vector",
      "python",
      "green",
      "blue",
      "venv",
      "typescript",
      "react",
      "frontend",
      "node",
      "start",
      "exit",
      "building",
      "installed",
      "cargo",
      "release",
      "prerequisites",
      "command"
    ],
    "summary": "This build script automates the compilation and setup process for a multi-language User Management System. It verifies prerequisites (Node.js, Rust, Python 3), installs dependencies, builds TypeScript components, Rust vector databases, Python environments, and React frontends. The script also runs comprehensive tests across all system components to ensure proper functionality."
  },
  "cacheInfo": {
    "cached": false,
    "hash": "445f7979cc319d9d5014975144784da925e1ab48feed628246872e82f7da0dcd"
  },
  "performance": {
    "totalTimeMs": 43744,
    "tokens": {
      "input": 832,
      "output": 1252,
      "total": 2084
    },
    "costUsd": 0.00046704000000000005
  }
}