{
  "classification": {
    "template": "compliance",
    "confidence": 0.95,
    "domain": "compliance",
    "docType": "Compliance Policy"
  },
  "graphStructure": {
    "cypher": "CREATE (doc:Document {\n      id: \"Privacy GDPR Policy\",\n      title: \"Privacy GDPR Policy\",\n      domain: \"compliance\",\n      doc_type: \"Compliance Policy\"\n    })\nCREATE (e0:Requirement {name: \"Lawfulness Transparency\", description: \"Obtain explicit consent for collecting personal data, provide privacy notices, and document legal processing.\", regulation: \"GDPR\", reference: \"Article 6, Article 12\"})\nCREATE (doc)-[:MENTIONS]->(e0)\nCREATE (e1:Requirement {name: \"Purpose Limitation\", description: \"Use personal data only for specified purposes, do not use for incompatible purposes, and delete when no longer necessary.\", regulation: \"GDPR\", reference: \"Article 5(1)(b)\"})\nCREATE (doc)-[:MENTIONS]->(e1)\nCREATE (e2:Requirement {name: \"Data Minimization\", description: \"Collect only necessary personal data, review collection practices, and implement retention schedules.\", regulation: \"GDPR\", reference: \"Article 5(1)(c)\"})\nCREATE (doc)-[:MENTIONS]->(e2)\nCREATE (e3:Requirement {name: \"Accuracy\", description: \"Maintain accurate and up-to-date records, and allow individuals to correct their data.\", regulation: \"GDPR\", reference: \"Article 5(1)(d)\"})\nCREATE (doc)-[:MENTIONS]->(e3)\nCREATE (e4:Requirement {name: \"Storage Limitation\", description: \"Retain personal data for specified periods: 7 years maximum for general data, 2 years for marketing after last contact, and as required by law for financial records.\", regulation: \"GDPR\", reference: \"Article 5(1)(e)\"})\nCREATE (doc)-[:MENTIONS]->(e4)\nCREATE (e5:Requirement {name: \"Security\", description: \"Implement encryption at rest and in transit, access controls, authentication, security assessments, and incident response procedures.\", regulation: \"GDPR\", reference: \"Article 32\"})\nCREATE (doc)-[:MENTIONS]->(e5)\nCREATE (e6:Requirement {name: \"Subject Rights\", description: \"Ensure rights to access, rectification, erasure, data portability, and objection for data subjects.\", regulation: \"GDPR\", reference: \"Articles 15-21\"})\nCREATE (doc)-[:MENTIONS]->(e6)\nCREATE (e7:Finding {name: \"No Explicit Consent Documented\", description: \"Policy requires explicit consent but no evidence of documented consent processes in place.\", status: \"Open\", severity: \"High\"})\nCREATE (doc)-[:MENTIONS]->(e7)\nCREATE (e8:Finding {name: \"Inadequate Retention Enforcement\", description: \"Retention periods specified, but no mechanisms to ensure deletion after maximum periods.\", status: \"Open\", severity: \"Medium\"})\nCREATE (doc)-[:MENTIONS]->(e8)\nCREATE (e9:Risk {name: \"Non-Compliance Penalties\", description: \"Risk of fines and legal actions due to failure to meet GDPR requirements.\", likelihood: \"High\", impact: \"High\"})\nCREATE (doc)-[:MENTIONS]->(e9)\nCREATE (e10:Risk {name: \"Data Breach\", description: \"Risk of unauthorized access or data loss due to insufficient security controls.\", likelihood: \"Medium\", impact: \"High\"})\nCREATE (doc)-[:MENTIONS]->(e10)",
    "entities": [
      {
        "type": "Requirement",
        "properties": {
          "name": "Lawfulness Transparency",
          "description": "Obtain explicit consent for collecting personal data, provide privacy notices, and document legal processing.",
          "regulation": "GDPR",
          "reference": "Article 6, Article 12"
        }
      },
      {
        "type": "Requirement",
        "properties": {
          "name": "Purpose Limitation",
          "description": "Use personal data only for specified purposes, do not use for incompatible purposes, and delete when no longer necessary.",
          "regulation": "GDPR",
          "reference": "Article 5(1)(b)"
        }
      },
      {
        "type": "Requirement",
        "properties": {
          "name": "Data Minimization",
          "description": "Collect only necessary personal data, review collection practices, and implement retention schedules.",
          "regulation": "GDPR",
          "reference": "Article 5(1)(c)"
        }
      },
      {
        "type": "Requirement",
        "properties": {
          "name": "Accuracy",
          "description": "Maintain accurate and up-to-date records, and allow individuals to correct their data.",
          "regulation": "GDPR",
          "reference": "Article 5(1)(d)"
        }
      },
      {
        "type": "Requirement",
        "properties": {
          "name": "Storage Limitation",
          "description": "Retain personal data for specified periods: 7 years maximum for general data, 2 years for marketing after last contact, and as required by law for financial records.",
          "regulation": "GDPR",
          "reference": "Article 5(1)(e)"
        }
      },
      {
        "type": "Requirement",
        "properties": {
          "name": "Security",
          "description": "Implement encryption at rest and in transit, access controls, authentication, security assessments, and incident response procedures.",
          "regulation": "GDPR",
          "reference": "Article 32"
        }
      },
      {
        "type": "Requirement",
        "properties": {
          "name": "Subject Rights",
          "description": "Ensure rights to access, rectification, erasure, data portability, and objection for data subjects.",
          "regulation": "GDPR",
          "reference": "Articles 15-21"
        }
      },
      {
        "type": "Finding",
        "properties": {
          "name": "No Explicit Consent Documented",
          "description": "Policy requires explicit consent but no evidence of documented consent processes in place.",
          "status": "Open",
          "severity": "High"
        }
      },
      {
        "type": "Finding",
        "properties": {
          "name": "Inadequate Retention Enforcement",
          "description": "Retention periods specified, but no mechanisms to ensure deletion after maximum periods.",
          "status": "Open",
          "severity": "Medium"
        }
      },
      {
        "type": "Risk",
        "properties": {
          "name": "Non-Compliance Penalties",
          "description": "Risk of fines and legal actions due to failure to meet GDPR requirements.",
          "likelihood": "High",
          "impact": "High"
        }
      },
      {
        "type": "Risk",
        "properties": {
          "name": "Data Breach",
          "description": "Risk of unauthorized access or data loss due to insufficient security controls.",
          "likelihood": "Medium",
          "impact": "High"
        }
      }
    ],
    "relationships": [
      {
        "type": "HAS_FINDING",
        "source": "Lawfulness Transparency",
        "target": "No Explicit Consent Documented",
        "properties": {}
      },
      {
        "type": "HAS_FINDING",
        "source": "Storage Limitation",
        "target": "Inadequate Retention Enforcement",
        "properties": {}
      },
      {
        "type": "MITIGATES",
        "source": "Security",
        "target": "Data Breach",
        "properties": {}
      }
    ]
  },
  "fulltextMetadata": {
    "title": "Privacy GDPR Policy",
    "domain": "compliance",
    "docType": "Compliance Policy",
    "extractedFields": {
      "requirement_name": [
        "Lawfulness Transparency",
        "Purpose Limitation",
        "Data Minimization",
        "Accuracy",
        "Storage Limitation",
        "Security",
        "Subject Rights"
      ],
      "requirement_description": [
        "Obtain explicit consent for collecting personal data, provide privacy notices, and document legal processing.",
        "Use personal data only for specified purposes, do not use for incompatible purposes, and delete when no longer necessary.",
        "Collect only necessary personal data, review collection practices, and implement retention schedules.",
        "Maintain accurate and up-to-date records, and allow individuals to correct their data.",
        "Retain personal data for specified periods: 7 years maximum for general data, 2 years for marketing after last contact, and as required by law for financial records.",
        "Implement encryption at rest and in transit, access controls, authentication, security assessments, and incident response procedures.",
        "Ensure rights to access, rectification, erasure, data portability, and objection for data subjects."
      ],
      "requirement_regulation": [
        "GDPR",
        "GDPR",
        "GDPR",
        "GDPR",
        "GDPR",
        "GDPR",
        "GDPR"
      ],
      "requirement_reference": [
        "Article 6, Article 12",
        "Article 5(1)(b)",
        "Article 5(1)(c)",
        "Article 5(1)(d)",
        "Article 5(1)(e)",
        "Article 32",
        "Articles 15-21"
      ],
      "finding_name": [
        "No Explicit Consent Documented",
        "Inadequate Retention Enforcement"
      ],
      "finding_description": [
        "Policy requires explicit consent but no evidence of documented consent processes in place.",
        "Retention periods specified, but no mechanisms to ensure deletion after maximum periods."
      ],
      "finding_status": [
        "Open",
        "Open"
      ],
      "finding_severity": [
        "High",
        "Medium"
      ],
      "risk_name": [
        "Non-Compliance Penalties",
        "Data Breach"
      ],
      "risk_description": [
        "Risk of fines and legal actions due to failure to meet GDPR requirements.",
        "Risk of unauthorized access or data loss due to insufficient security controls."
      ],
      "risk_likelihood": [
        "High",
        "Medium"
      ],
      "risk_impact": [
        "High",
        "High"
      ]
    },
    "keywords": [
      "data",
      "compliance",
      "right",
      "personal",
      "privacy",
      "gdpr",
      "policy",
      "date",
      "legal",
      "purpose",
      "protection",
      "limitation",
      "collect",
      "only",
      "purposes",
      "retention",
      "records",
      "regular",
      "years",
      "security"
    ],
    "summary": "This policy establishes GDPR and data protection compliance requirements for all personnel handling personal data. It outlines six core principles including lawful processing, data minimization, and security measures like encryption and access controls. The policy also defines data subject rights and designates a compliance officer for implementation and oversight."
  },
  "cacheInfo": {
    "cached": false,
    "hash": "b7d8c173827d95166be1db09ee59462d61ee769e0c7740da9c754cfd7655d33b"
  },
  "performance": {
    "totalTimeMs": 39621,
    "tokens": {
      "input": 1686,
      "output": 983,
      "total": 2669
    },
    "costUsd": 0.0005112800000000001
  }
}