{
  "classification": {
    "template": "customer_support",
    "confidence": 0.95,
    "domain": "customer_support",
    "docType": "Support Ticket"
  },
  "graphStructure": {
    "cypher": "CREATE (doc:Document {\n      id: \"Support Ticket #CS-2025-1842\",\n      title: \"Support Ticket #CS-2025-1842\",\n      domain: \"customer_support\",\n      doc_type: \"Support Ticket\"\n    })\nCREATE (e0:Ticket {id: \"CS-2025-1842\", customer: \"Acme Corporation\", reported_by: \"Alice Brown\", email: \"alice.brown@acme.com\", priority: \"High\", status: \"In Progress\", created: \"January 26, 2025 10:30 AM\", assigned_to: \"Tom Wilson (Support) + Team\", next_update: \"January 27, 2025\", sla_metrics: \"48 hours for follow-up\"})\nCREATE (doc)-[:MENTIONS]->(e0)\nCREATE (e1:Issue {description: \"File synchronization failing for files larger than 100MB, gets stuck at 67% and eventually times out\", steps_to_reproduce: \"Attempt to sync a 150MB file, observe progress stalling at approximately 67%\", impact: \"Affects 15 users, blocking design work\", category: \"Synchronization Failure\", root_cause: \"Chunk size set to 10MB causing timeouts\"})\nCREATE (doc)-[:MENTIONS]->(e1)\nCREATE (e2:Resolution {steps: \"Reduce chunk size to 5MB, deploy fix to production\", deployment_eta: \"January 27, 2025 9:00 AM\", communication: \"Email sent to Alice Brown with ETA update\", follow_up: \"Follow up with customer within 48 hours\"})\nCREATE (doc)-[:MENTIONS]->(e2)",
    "entities": [
      {
        "type": "Ticket",
        "properties": {
          "id": "CS-2025-1842",
          "customer": "Acme Corporation",
          "reported_by": "Alice Brown",
          "email": "alice.brown@acme.com",
          "priority": "High",
          "status": "In Progress",
          "created": "January 26, 2025 10:30 AM",
          "assigned_to": "Tom Wilson (Support) + Team",
          "next_update": "January 27, 2025",
          "sla_metrics": "48 hours for follow-up"
        }
      },
      {
        "type": "Issue",
        "properties": {
          "description": "File synchronization failing for files larger than 100MB, gets stuck at 67% and eventually times out",
          "steps_to_reproduce": "Attempt to sync a 150MB file, observe progress stalling at approximately 67%",
          "impact": "Affects 15 users, blocking design work",
          "category": "Synchronization Failure",
          "root_cause": "Chunk size set to 10MB causing timeouts"
        }
      },
      {
        "type": "Resolution",
        "properties": {
          "steps": "Reduce chunk size to 5MB, deploy fix to production",
          "deployment_eta": "January 27, 2025 9:00 AM",
          "communication": "Email sent to Alice Brown with ETA update",
          "follow_up": "Follow up with customer within 48 hours"
        }
      }
    ],
    "relationships": [
      {
        "type": "HAS_ISSUE",
        "source": "CS-2025-1842",
        "target": "File synchronization failing for files larger than 100MB, gets stuck at 67% and eventually times out",
        "properties": {}
      },
      {
        "type": "RESOLVED_BY",
        "source": "File synchronization failing for files larger than 100MB, gets stuck at 67% and eventually times out",
        "target": "Reduce chunk size to 5MB, deploy fix to production",
        "properties": {}
      }
    ]
  },
  "fulltextMetadata": {
    "title": "Support Ticket #CS-2025-1842",
    "domain": "customer_support",
    "docType": "Support Ticket",
    "extractedFields": {},
    "keywords": []
  },
  "cacheInfo": {
    "cached": false,
    "hash": "9210093729e5407e068502928214ebc4866d15030132fcd05e8fa9c7f9b7d687"
  },
  "performance": {
    "totalTimeMs": 23192,
    "tokens": {
      "input": 1770,
      "output": 600,
      "total": 2370
    },
    "costUsd": 0.0004158
  }
}